{
  "walls": [
    {
      "id": "wall_0",
      "vertices": [
        [
          0.1,
          0.1
        ],
        [
          0.9,
          0.1
        ],
        [
          0.9,
          0.15
        ],
        [
          0.1,
          0.15
        ]
      ],
      "center": [
        0.5,
        0.125
      ],
      "thickness": 0.05
    },
    {
      "id": "wall_1",
      "vertices": [
        [
          0.85,
          0.1
        ],
        [
          0.9,
          0.1
        ],
        [
          0.9,
          0.6
        ],
        [
          0.85,
          0.6
        ]
      ],
      "center": [
        0.875,
        0.35
      ],
      "thickness": 0.05
    },
    {
      "id": "wall_2",
      "vertices": [
        [
          0.55,
          0.55
        ],
        [
          0.9,
          0.55
        ],
        [
          0.9,
          0.6
        ],
        [
          0.55,
          0.6
        ]
      ],
      "center": [
        0.725,
        0.575
      ],
      "thickness": 0.05
    },
    {
      "id": "wall_3",
      "vertices": [
        [
          0.55,
          0.55
        ],
        [
          0.6,
          0.55
        ],
        [
          0.6,
          0.9
        ],
        [
          0.55,
          0.9
        ]
      ],
      "center": [
        0.575,
        0.725
      ],
      "thickness": 0.05
    },
    {
      "id": "wall_4",
      "vertices": [
        [
          0.1,
          0.85
        ],
        [
          0.6,
          0.85
        ],
        [
          0.6,
          0.9
        ],
        [
          0.1,
          0.9
        ]
      ],
      "center": [
        0.35,
        0.875
      ],
      "thickness": 0.05
    },
    {
      "id": "wall_5",
      "vertices": [
        [
          0.1,
          0.1
        ],
        [
          0.15,
          0.1
        ],
        [
          0.15,
          0.9
        ],
        [
          0.1,
          0.9
        ]
      ],
      "center": [
        0.125,
        0.5
      ],
      "thickness": 0.05
    },
    {
      "id": "wall_6",
      "vertices": [
        [
          0.4,
          0.15
        ],
        [
          0.45,
          0.15
        ],
        [
          0.45,
          0.55
        ],
        [
          0.4,
          0.55
        ]
      ],
      "center": [
        0.425,
        0.35
      ],
      "thickness": 0.05
    },
    {
      "id": "wall_7",
      "vertices": [
        [
          0.15,
          0.4
        ],
        [
          0.4,
          0.4
        ],
        [
          0.4,
          0.45
        ],
        [
          0.15,
          0.45
        ]
      ],
      "center": [
        0.275,
        0.425
      ],
      "thickness": 0.05
    }
  ],
  "doors": [
    {
      "id": "door_0",
      "center": [
        0.3,
        0.125
      ],
      "width": 0.06,
      "height": 0.03,
      "type": "opening"
    },
    {
      "id": "door_1",
      "center": [
        0.425,
        0.25
      ],
      "width": 0.03,
      "height": 0.06,
      "type": "opening"
    },
    {
      "id": "door_2",
      "center": [
        0.25,
        0.425
      ],
      "width": 0.06,
      "height": 0.03,
      "type": "opening"
    }
  ],
  "windows": [
    {
      "id": "window_0",
      "center": [
        0.7,
        0.125
      ],
      "width": 0.05,
      "height": 0.02
    },
    {
      "id": "window_1",
      "center": [
        0.875,
        0.25
      ],
      "width": 0.02,
      "height": 0.05
    },
    {
      "id": "window_2",
      "center": [
        0.125,
        0.3
      ],
      "width": 0.02,
      "height": 0.05
    },
    {
      "id": "window_3",
      "center": [
        0.125,
        0.7
      ],
      "width": 0.02,
      "height": 0.05
    }
  ],
  "rooms": [
    {
      "id": "room_0",
      "center": [
        0.275,
        0.25
      ],
      "bounds": {
        "x": 0.15,
        "y": 0.15,
        "width": 0.25,
        "height": 0.25
      }
    },
    {
      "id": "room_1",
      "center": [
        0.675,
        0.25
      ],
      "bounds": {
        "x": 0.45,
        "y": 0.15,
        "width": 0.4,
        "height": 0.4
      }
    },
    {
      "id": "room_2",
      "center": [
        0.325,
        0.675
      ],
      "bounds": {
        "x": 0.15,
        "y": 0.45,
        "width": 0.35,
        "height": 0.4
      }
    },
    {
      "id": "room_3",
      "center": [
        0.725,
        0.725
      ],
      "bounds": {
        "x": 0.6,
        "y": 0.6,
        "width": 0.25,
        "height": 0.25
      }
    }
  ],
  "image_width": 800,
  "image_height": 600,
  "scale_factor": 12.0
}